README.md
setup.cfg
setup.py
scoria/AtomsAndBonds.py
scoria/FileIO.py
scoria/Geometry.py
scoria/Information.py
scoria/Manipulation.py
scoria/Molecule.py
scoria/OtherMolecules.py
scoria/Quaternion.py
scoria/Selections.py
scoria/Test.py
scoria/UnitTests.py
scoria/__init__.py
scoria/__main__.py
scoria/six.py
scoria.egg-info/PKG-INFO
scoria.egg-info/SOURCES.txt
scoria.egg-info/dependency_links.txt
scoria.egg-info/requires.txt
scoria.egg-info/top_level.txt
scoria/dumbpy/Array.py
scoria/dumbpy/DType.py
scoria/dumbpy/Support.py
scoria/dumbpy/Utils.py
scoria/dumbpy/__init__.py
scoria/sample-files/3_mol_test.pdb
scoria/sample-files/DNA_RNA_Protein.pdb
scoria/sample-files/M2_traj.dcd
scoria/sample-files/M2_traj.psf
scoria/sample-files/file_io_test.pdb
scoria/sample-files/other_mol_test.pdb
scoria/sample-files/single_frame.100.dcd
scoria/sample-files/single_frame.dcd
scoria/sample-files/single_frame.pdb
scoria/sample-files/single_frame.pdbqt
scoria/sample-files/single_frame.psf
scoria/sample-files/test_sim.pdb
scoria/unittests/FileIOTests.py
scoria/unittests/GeometryTests.py
scoria/unittests/InformationTests.py
scoria/unittests/ManipulationTests.py
scoria/unittests/OtherMoleculeTests.py
scoria/unittests/QuarternionTests.py
scoria/unittests/SelectionTests.py
scoria/unittests/UnitTests.py
scoria/unittests/__init__.py
test/test.py