Metadata-Version: 1.1
Name: scoria
Version: 1.0.4
Summary: A lightweight molecule manipulation codebase.
Home-page: https://git.durrantlab.com/jdurrant/scoria
Author: Jacob Durrant
Author-email: durrantj@pitt.edu
License: UNKNOWN
Download-URL: https://git.durrantlab.com/jdurrant/scoria/repository/archive.tar.gz
Platform: UNKNOWN
Classifier: Development Status :: 5 - Production/Stable
Classifier: Natural Language :: English
Classifier: Operating System :: OS Independent
Classifier: License :: OSI Approved :: MIT License
Classifier: Programming Language :: Python :: 2
Classifier: Programming Language :: Python :: 3
Classifier: Topic :: Scientific/Engineering :: Bio-Informatics
Classifier: Topic :: Scientific/Engineering :: Chemistry
Classifier: Intended Audience :: Science/Research
